xonsh_jupyter/__init__.py
xonsh_jupyter/alias.py
xonsh_jupyter/kernel.py
xonsh_jupyter/shell.py
xonsh_jupyter/resources/__init__.py
xonsh_jupyter/resources/logo-svg.svg
xontrib/jupyter.py
xontrib_jupyter-0.3.3.dist-info/METADATA
xontrib_jupyter-0.3.3.dist-info/WHEEL
xontrib_jupyter-0.3.3.dist-info/licenses/LICENSE
xontrib_jupyter-0.3.3.dist-info/RECORD
