Metadata-Version: 2.4
Name: xontrib-jupyter
Version: 0.3.3
Summary: Xonsh kernel for Jupyter Notebook and Jupyter Lab allows to execute xonsh shell commands in a notebook cell
Project-URL: Repository, https://github.com/xonsh/xontrib-jupyter
Project-URL: Documentation, https://github.com/xonsh/xontrib-jupyter/blob/master/README.md
Project-URL: Code, https://github.com/xonsh/xontrib-jupyter
Project-URL: Issue tracker, https://github.com/xonsh/xontrib-jupyter/issues
Author-email: Xonsh Dev <jnoortheen@gmail.com>
License-Expression: MIT
License-File: LICENSE
Keywords: xonsh,xontrib
Classifier: Intended Audience :: Developers
Classifier: License :: OSI Approved :: MIT License
Classifier: Natural Language :: English
Classifier: Operating System :: OS Independent
Classifier: Programming Language :: Python
Classifier: Programming Language :: Python :: 3
Classifier: Programming Language :: Python :: 3.6
Classifier: Programming Language :: Python :: 3.7
Classifier: Programming Language :: Python :: 3.8
Classifier: Topic :: System :: Shells
Classifier: Topic :: System :: System Shells
Classifier: Topic :: Terminals
Requires-Python: >=3.9
Requires-Dist: jupyter-client>=8
Requires-Dist: xonsh>=0.19
Provides-Extra: dev
Requires-Dist: pytest>=6.0; extra == 'dev'
